telegram_analyzer/__init__.py
telegram_analyzer/analyzer.py
telegram_analyzer/auth.py
telegram_analyzer/main.py
telegram_analyzer/online_presence_analyzer.py
telegram_analyzer/parser.py
telegram_analyzer/report.py
telegram_analyzer/stats_export.py
telegram_analyzer/utils.py
telegram_analyzer/visualizer.py
telegram_analyzer/web_server.py
telegram_analyzer/templates/404.html
telegram_analyzer/templates/account.html
telegram_analyzer/templates/analysis.html
telegram_analyzer/templates/index.html
telegram_analyzer/templates/login.html
telegram_analyzer/templates/register.html
telegram_analyzer/templates/upload.html
telegram_analyzer-1.0.0.dist-info/METADATA
telegram_analyzer-1.0.0.dist-info/WHEEL
telegram_analyzer-1.0.0.dist-info/entry_points.txt
telegram_analyzer-1.0.0.dist-info/top_level.txt
telegram_analyzer-1.0.0.dist-info/RECORD
