Metadata-Version: 2.4
Name: telegram-analyzer
Version: 1.0.0
Summary: A toolkit for analyzing Telegram chat exports
Author: Your Name
Author-email: your.email@example.com
Keywords: telegram,analysis,visualization,chat
Requires-Python: >=3.7
Requires-Dist: pandas>=1.0.0
Requires-Dist: numpy>=1.18.0
Requires-Dist: matplotlib>=3.1.0
Requires-Dist: seaborn>=0.10.0
Requires-Dist: nltk>=3.5.0
Requires-Dist: tqdm>=4.0.0
Requires-Dist: wordcloud>=1.8.0
Requires-Dist: emoji>=1.2.0
Provides-Extra: interactive
Requires-Dist: plotly>=5.0.0; extra == "interactive"
Requires-Dist: networkx>=2.6.0; extra == "interactive"
Requires-Dist: scipy>=1.7.0; extra == "interactive"
Provides-Extra: web
Requires-Dist: flask>=3.0.0; extra == "web"
Provides-Extra: auth
Requires-Dist: flask>=3.0.0; extra == "auth"
Provides-Extra: full
Requires-Dist: plotly>=5.0.0; extra == "full"
Requires-Dist: networkx>=2.6.0; extra == "full"
Requires-Dist: scipy>=1.7.0; extra == "full"
Requires-Dist: textblob>=0.15.0; extra == "full"
Requires-Dist: flask>3.0.0; extra == "full"
Dynamic: author
Dynamic: author-email
Dynamic: keywords
Dynamic: provides-extra
Dynamic: requires-dist
Dynamic: requires-python
Dynamic: summary
